mcp_mcp_server_demo_a_b/__init__.py
mcp_mcp_server_demo_a_b-0.1.0.dist-info/METADATA
mcp_mcp_server_demo_a_b-0.1.0.dist-info/WHEEL
mcp_mcp_server_demo_a_b-0.1.0.dist-info/entry_points.txt
mcp_mcp_server_demo_a_b-0.1.0.dist-info/RECORD
