Metadata-Version: 2.4
Name: mcp-mcp-server-demo-a-b
Version: 0.1.0
Summary: Add your description here
Author-email: barreler126 <barreler@126.com>
Requires-Python: >=3.13
Requires-Dist: mcp[cli]>=1.11.0
